kernelbiome/__init__.py
kernelbiome/helpers_analysis.py
kernelbiome/helpers_fitting.py
kernelbiome/helpers_jax.py
kernelbiome/kernelbiome.py
kernelbiome/kernels_jax.py
kernelbiome/kernels_weighted_jax.py
kernelbiome/metrics_jax.py
kernelbiome-1.0.2.dist-info/LICENSE
kernelbiome-1.0.2.dist-info/METADATA
kernelbiome-1.0.2.dist-info/WHEEL
kernelbiome-1.0.2.dist-info/top_level.txt
kernelbiome-1.0.2.dist-info/RECORD
