Metadata-Version: 2.1
Name: kernelbiome
Version: 1.0.2
Summary: A kernel-based nonparametric regression and classification framework for compositional data.
Home-page: https://github.com/shimenghuang/KernelBiome
Author: Shimeng Huang, Elisabeth Ailer, Niki Kilbertus, Niklas Pfister
Author-email: shimeng@math.ku.dk, elisabeth.ailer@helmholtz-muenchen.de, niki.kilbertus@helmholtz-munich.de, np@math.ku.dk
Project-URL: Bug Tracker, https://github.com/shimenghuang/KernelBiome/issues
Classifier: Programming Language :: Python :: 3
Classifier: License :: OSI Approved :: MIT License
Classifier: Operating System :: OS Independent
Requires-Python: >=3.9
License-File: LICENSE
Requires-Dist: numpy (>=1.22.3)
Requires-Dist: pandas (>=1.3.5)
Requires-Dist: scikit-learn (>=1.0.1)
Requires-Dist: jaxlib (>=0.1.75)
Requires-Dist: jax (>=0.2.26)
Requires-Dist: matplotlib (>=3.5.1)
